r2r_ctd/__init__.py
r2r_ctd/__main__.py
r2r_ctd/accessors.py
r2r_ctd/breakout.py
r2r_ctd/checks.py
r2r_ctd/derived.py
r2r_ctd/docker_ctl.py
r2r_ctd/exceptions.py
r2r_ctd/maps.py
r2r_ctd/reporting.py
r2r_ctd/state.py
r2r_ctd/sbe/__init__.py
r2r_ctd/sbe/batch.txt
r2r_ctd/sbe/binavg_template.xml
r2r_ctd/sbe/datcnv_allsensors.xml
r2r_ctd/sbe/datcnv_template.xml
r2r_ctd/sbe/derive_template.xml
r2r_ctd/sbe/sensors.toml
r2r_ctd-2025.12.0.dist-info/licenses/LICENSE.md
r2r_ctd-2025.12.0.dist-info/METADATA
r2r_ctd-2025.12.0.dist-info/WHEEL
r2r_ctd-2025.12.0.dist-info/entry_points.txt
r2r_ctd-2025.12.0.dist-info/top_level.txt
r2r_ctd-2025.12.0.dist-info/RECORD
