Metadata-Version: 2.4
Name: r2r-ctd
Version: 2025.12.0
Summary: Add your description here
Author-email: Andrew Barna <abarna@gmail.com>
License-Expression: BSD-3-Clause
Requires-Python: >=3.13
License-File: LICENSE.md
Requires-Dist: click>=8.2.0
Requires-Dist: docker>=7.1.0
Requires-Dist: lxml>=5.4.0
Requires-Dist: odf-sbe>=0.2.1
Requires-Dist: rich>=14.0.0
Requires-Dist: folium>=0.20.0
Dynamic: license-file
